mocanexion/__init__.py
mocanexion2-0.5.dist-info/LICENSE.txt
mocanexion2-0.5.dist-info/METADATA
mocanexion2-0.5.dist-info/WHEEL
mocanexion2-0.5.dist-info/top_level.txt
mocanexion2-0.5.dist-info/RECORD
