Metadata-Version: 2.1
Name: mocanexion2
Version: 0.5
Summary: Python connection to MOCA-WMS 2017 - 2018 - 2019 - 2020
Home-page: https://github.com/Hittwar/mocanexion2
Author: Hittwar
Author-email: hittwar@hotmail.com
License: The Unlicense
Keywords: moca wms
Platform: UNKNOWN
Requires-Python: >=3
Requires-Dist: pandas
Requires-Dist: requests
